{
  "gitSyncId": "673b75dbb612100709611140_997a0297-b9ef-4638-844a-a77651713d2f",
  "id": "ShopPage_rapiApi",
  "pluginId": "restapi-plugin",
  "pluginType": "API",
  "unpublishedAction": {
    "actionConfiguration": {
      "autoGeneratedHeaders": [],
      "body": "",
      "bodyFormData": [],
      "encodeParamsToggle": true,
      "formData": {
        "apiContentType": "none"
      },
      "headers": [],
      "httpMethod": "GET",
      "httpVersion": "HTTP11",
      "paginationType": "NONE",
      "path": "/electronics/phones",
      "pluginSpecifiedTemplates": [
        {
          "value": true
        }
      ],
      "queryParameters": [
        {
          "key": "search",
          "value": "smartphone"
        }
      ],
      "timeoutInMillisecond": 10000
    },
    "confirmBeforeExecute": false,
    "datasource": {
      "datasourceConfiguration": {
        "url": "https://api.rapidapi.com"
      },
      "isAutoGenerated": false,
      "name": "DEFAULT_REST_DATASOURCE",
      "pluginId": "restapi-plugin"
    },
    "dynamicBindingPathList": [],
    "executeOnLoad": false,
    "name": "rapiApi",
    "pageId": "ShopPage",
    "userSetOnLoad": false
  }
}